watchcode/__init__.py
watchcode/cli.py
watchcode/client.py
watchcode/config.py
watchcode/crypto.py
watchcode/hooks.py
watchcode/scripts/__init__.py
watchcode/scripts/apns_sender.py
watchcode/scripts/hook_handler.py
watchcode_cli-1.0.21.dist-info/licenses/LICENSE
watchcode_cli-1.0.21.dist-info/METADATA
watchcode_cli-1.0.21.dist-info/WHEEL
watchcode_cli-1.0.21.dist-info/entry_points.txt
watchcode_cli-1.0.21.dist-info/top_level.txt
watchcode_cli-1.0.21.dist-info/RECORD
