Metadata-Version: 2.4
Name: watchcode-cli
Version: 1.0.21
Summary: Send Claude Code notifications to your Apple Watch
Author: WatchCode Contributors
License: MIT
Project-URL: Homepage, https://github.com/egor-gm/WatchCode
Project-URL: Repository, https://github.com/egor-gm/WatchCode
Project-URL: Issues, https://github.com/egor-gm/WatchCode/issues
Keywords: claude,claude-code,apple-watch,notifications,apns
Classifier: Development Status :: 4 - Beta
Classifier: Intended Audience :: Developers
Classifier: License :: OSI Approved :: MIT License
Classifier: Programming Language :: Python :: 3
Classifier: Programming Language :: Python :: 3.8
Classifier: Programming Language :: Python :: 3.9
Classifier: Programming Language :: Python :: 3.10
Classifier: Programming Language :: Python :: 3.11
Classifier: Programming Language :: Python :: 3.12
Requires-Python: >=3.8
License-File: LICENSE
Requires-Dist: httpx[http2]>=0.24.0
Requires-Dist: click>=8.0.0
Requires-Dist: keyring>=24.0.0
Requires-Dist: requests>=2.28.0
Requires-Dist: ecdsa>=0.18.0
Requires-Dist: cryptography>=41.0.0
Dynamic: license-file
